[
    {
        "id": 1,
        "name": "Chanel No. 5",
        "price": 50,
        "image": "images/chanel-no5.jpg",
        "description": "A timeless fragrance that embodies elegance and luxury.",
        "brand": "Chanel",
        "size": "100ml",
        "type": "Floral Aldehyde"
    },
    {
        "id": 2,
        "name": "Gucci Bloom",
        "price": 60,
        "image": "images/gucci-bloom.jpg",
        "description": "A floral fragrance inspired by the gardens of Florence.",
        "brand": "Gucci",
        "size": "50ml",
        "type": "Floral"
    }
]